{
  "exam": {
    "examNumber": 38,
    "examDate": "2018-04-28",
    "examType": "advanced",
    "totalQuestions": 50,
    "timeLimitMinutes": 80,
    "isFree": true,
    "id": 32
  },
  "questions": [
    {
      "content": "(가) 시대의 생활 모습으로 옳은 것은?",
      "choices": [
        "거푸집을 이용하여 도구를 제작하였다.",
        "지배자의 무덤으로 고인돌을 축조하였다.",
        "반달돌칼을 이용하여 곡식을 수확하였다.",
        "가락바퀴와 뼈바늘을 이용하여 옷을 지었다.",
        "주로 동굴이나 강가의 막집에서 거주하였다."
      ],
      "correctAnswer": 5,
      "points": 1,
      "era": "선사·고조선",
      "category": "사회",
      "difficulty": 3,
      "id": 38001,
      "examId": 32,
      "questionNumber": 1,
      "keywords": [
        "고인돌",
        "반달돌칼",
        "가락바퀴",
        "뼈바늘",
        "동굴"
      ],
      "explanation": "주어진 선지 ⑤번은 구석기 시대 사람들의 생활 모습을 정확히 나타냅니다. 구석기인들은 이동하며 사냥과 채집 생활을 하였으므로, 주로 동굴이나 강가의 막집 등 임시 거처에서 거주하였습니다. 나머지 선지들은 다른 시대를 설명합니다. ①번 거푸집을 이용한 도구 제작과 ②번 고인돌 축조는 청동기 시대의 특징이며, ③번 반달돌칼을 이용한 곡식 수확은 신석기~청동기 시대, ④번 가락바퀴와 뼈바늘을 이용한 옷 제작은 신석기 시대의 생활 모습입니다."
    },
    {
      "content": "다음 사건이 일어난 시기를 연표에서 옳게 고른 것은?",
      "choices": [
        "(가)",
        "(나)",
        "(다)",
        "(라)",
        "(마)"
      ],
      "correctAnswer": 3,
      "points": 2,
      "era": "삼국",
      "category": "정치",
      "difficulty": 3,
      "id": 38002,
      "examId": 32,
      "questionNumber": 2,
      "keywords": [
        "사건",
        "삼국 시대",
        "연표"
      ],
      "explanation": "제시된 사건은 고대 국가 체제를 갖춰가며 경쟁하던 삼국 시대의 주요 정치적 흐름 속에서 발생한 일입니다. 연표에서 (다)는 고구려, 백제, 신라가 각기 왕권을 강화하고 율령을 반포하며 영토를 확장하던 삼국 시기를 정확히 보여줍니다. 따라서 해당 사건이 일어난 시기는 (다)로 고르는 것이 적절합니다. (가)는 삼국 시대 이전, (나)는 원삼국 시대, (라)는 통일 신라와 발해 시대, (마)는 고려 또는 조선 시대를 나타내므로 제시된 사건의 시기와는 거리가 있습니다."
    },
    {
      "content": "(가), (나) 나라에 대한 설명으로 옳은 것은?",
      "choices": [
        "(가) - 여러 가(加)들이 별도로 사출도를 주관하였다.",
        "(가) - 박, 석, 김의 3성이 교대로 왕위를 계승하였다.",
        "(나) - 10월에 무천이라는 제천 행사를 열었다.",
        "(나) - 읍락 간의 경계를 중시하는 책화가 있었다.",
        "(가), (나) - 제사장인 천군과 신성 지역인 소도가 있었다."
      ],
      "correctAnswer": 1,
      "points": 3,
      "era": "선사·고조선",
      "category": "정치",
      "difficulty": 3,
      "id": 38003,
      "examId": 32,
      "questionNumber": 3,
      "keywords": [
        "부여",
        "사출도",
        "신라",
        "동예",
        "무천"
      ],
      "explanation": "정답은 ①번입니다. ①번 선지는 (가) 국가의 여러 가(加)들이 별도로 사출도를 주관했다고 설명하는데, 이는 부여의 독특한 5부족 연맹체 정치 체제(왕과 마가, 우가, 저가, 구가 등 대가들이 사출도 지배)를 정확히 나타냅니다.\n\n오답 선지들은 다음과 같습니다.\n② (가)에 대한 설명으로 제시된 '박, 석, 김의 3성이 교대로 왕위를 계승'한 것은 신라 초기의 특징입니다.\n③, ④ (나)에 대한 설명으로 제시된 '10월에 무천이라는 제천 행사를 열었다'거나 '읍락 간의 경계를 중시하는 책화가 있었다'는 동예의 특징입니다.\n⑤ (가), (나)에 대한 설명으로 제시된 '제사장인 천군과 신성 지역인 소도가 있었다'는 삼한의 특징입니다.\n\n이 문제의 핵심은 초기 국가인 부여, 고구려, 옥저, 동예, 삼한의 정치·사회적 특징을 정확히 구분하는 것입니다. 각 나라는 고유한 지배 체제와 풍습을 가지고 있었으며, 특히 부여의 사출도와 여러 가(加)의 역할은 중요한 특징입니다."
    },
    {
      "content": "(가) 인물에 대한 설명으로 옳은 것은?",
      "choices": [
        "대승기신론소, 십문화쟁론을 저술하였다.",
        "화랑도의 규범으로 세속 5계를 제시하였다.",
        "화엄일승법계도를 지어 화엄종을 정리하였다.",
        "인도와 중앙아시아를 여행하고 왕오천축국전을 지었다.",
        "당에서 귀국하여 황룡사 구층 목탑의 건립을 건의하였다."
      ],
      "correctAnswer": 1,
      "points": 2,
      "era": "삼국",
      "category": "문화",
      "difficulty": 3,
      "id": 38004,
      "examId": 32,
      "questionNumber": 4,
      "keywords": [
        "대승기신론소",
        "십문화쟁론",
        "화엄일승법계도",
        "왕오천축국전",
        "황룡사 구층 목탑"
      ],
      "explanation": "(가) 인물은 신라의 고승 원효입니다. 원효는 『대승기신론소』, 『금강삼매경론』, 『십문화쟁론』 등 수많은 저술을 통해 불교 사상 간의 대립을 조화시키고 복잡한 불교 교리를 대중화하는 데 크게 기여했습니다.\n\n② 세속 5계를 제시한 인물은 원광이며, ③ 화엄일승법계도를 지어 화엄종을 정리한 인물은 의상입니다. ④ 인도와 중앙아시아를 여행하고 『왕오천축국전』을 지은 인물은 혜초이며, ⑤ 황룡사 구층 목탑의 건립을 건의한 인물은 자장입니다. 이처럼 원효는 신라 중대의 대표적인 사상가로서 불교 통합과 대중화에 중요한 발자취를 남겼습니다."
    },
    {
      "content": "(가), (나) 무덤 양식에 대한 설명으로 옳은 것은?",
      "choices": [
        "(가) - 모줄임 천장 구조로 되어 있다.",
        "(가) - 무덤의 둘레돌에 12지 신상을 새겼다.",
        "(나) - 대표적인 무덤으로 황남대총이 있다.",
        "(나) - 내부의 천장과 벽에 그림을 그리기도 하였다.",
        "(가), (나) - 중국 남조의 영향을 받아 만들어졌다."
      ],
      "correctAnswer": 4,
      "points": 2,
      "era": "삼국",
      "category": "문화",
      "difficulty": 3,
      "id": 38005,
      "examId": 32,
      "questionNumber": 5,
      "keywords": [
        "모줄임 천장 구조",
        "12지 신상",
        "황남대총",
        "중국 남조"
      ],
      "explanation": "(나)는 굴식 돌방무덤(횡혈식 석실분)을 의미하며, 내부의 넓은 돌방 천장과 벽면에 그림을 그리는 것이 큰 특징입니다. 이는 고구려, 백제, 신라에서 널리 사용된 무덤 양식으로, 벽화를 통해 당시 사람들의 생활상과 사상을 엿볼 수 있습니다.\n오답 선지 ① 모줄임 천장 구조는 굴식 돌방무덤의 특징이며, ② 12지 신상 둘레돌은 통일 신라 시대 굴식 돌방무덤에서 나타납니다. ③ 황남대총은 (가)에 해당하는 돌무지 덧널무덤이며, ⑤ (가) 돌무지 덧널무덤은 신라 고유의 양식으로 중국 남조의 영향을 받지 않았습니다."
    },
    {
      "content": "(가) 나라의 문화유산으로 옳은 것은?",
      "choices": [
        "",
        "",
        "",
        "",
        ""
      ],
      "correctAnswer": 5,
      "points": 2,
      "era": "삼국",
      "category": "문화",
      "difficulty": 3,
      "id": 38006,
      "examId": 32,
      "questionNumber": 6,
      "keywords": [],
      "explanation": "정답인 ⑤는 백제 금동대향로로, 제시된 자료를 통해 (가) 나라가 백제임을 알 수 있는 대표적인 문화유산입니다. 백제 금동대향로는 뛰어난 공예 기술과 도교 및 불교 사상이 융합된 백제 예술의 정수를 보여주는 걸작입니다. 나머지 선지들은 고구려나 신라 등 다른 삼국시대 국가의 문화유산이거나, 시대가 다른 유산이므로 (가) 나라의 문화유산에 해당하지 않습니다. 백제는 삼국시대 동안 중국 남조와 활발히 교류하며 독자적이면서도 세련된 문화를 발전시켰습니다."
    },
    {
      "content": "(가), (나) 사이의 시기에 있었던 사실로 옳은 것은?",
      "choices": [
        "광개토 대왕이 신라에 침입한 왜를 물리쳤다.",
        "진흥왕이 화랑도를 국가 조직으로 개편하였다.",
        "소수림왕이 태학을 설립하고 율령을 반포하였다.",
        "개로왕이 고구려를 견제하고자 북위에 국서를 보냈다.",
        "근초고왕이 평양성을 공격하여 고국원왕을 전사시켰다."
      ],
      "correctAnswer": 4,
      "points": 3,
      "era": "삼국",
      "category": "정치",
      "difficulty": 3,
      "id": 38007,
      "examId": 32,
      "questionNumber": 7,
      "keywords": [
        "광개토 대왕",
        "진흥왕",
        "소수림왕",
        "개로왕",
        "근초고왕"
      ],
      "explanation": "정답은 ④번입니다. 5세기 후반, 고구려 장수왕의 남진 정책으로 심각한 위협을 받던 백제 개로왕은 472년에 고구려를 견제하고자 북위에 국서를 보내 군사적 지원을 요청했습니다. 이는 당시 백제가 고구려의 압박 속에서 외교적 돌파구를 찾으려 했던 중요한 시도였습니다.\n\n다른 선지들은 시기적으로 맞지 않습니다. ① 광개토 대왕의 신라 구원(5세기 초), ⑤ 근초고왕의 평양성 공격(4세기 중반), ③ 소수림왕의 태학 설립 및 율령 반포(4세기 후반)는 모두 개로왕의 북위 국서 발송보다 이전 시기입니다. 한편, ② 진흥왕의 화랑도 국가 조직 개편(6세기 중반)은 5세기 후반보다 이후의 일입니다."
    },
    {
      "content": "(가)~(라)를 시행한 순서대로 옳게 나열한 것은?",
      "choices": [
        "(가) - (나) - (다) - (라)",
        "(가) - (다) - (라) - (나)",
        "(나) - (라) - (가) - (다)",
        "(다) - (나) - (가) - (라)",
        "(라) - (가) - (나) - (다)"
      ],
      "correctAnswer": 1,
      "points": 2,
      "era": "남북국",
      "category": "경제",
      "difficulty": 3,
      "id": 38008,
      "examId": 32,
      "questionNumber": 8,
      "keywords": [],
      "explanation": "제시된 문제의 (가), (나), (다), (라) 항목의 구체적인 내용이 포함되어 있지 않아 정확한 해설을 제공하기 어렵습니다. 문제의 항목들을 알려주시면 해당 문제에 대한 해설을 작성해 드리겠습니다."
    },
    {
      "content": "다음 검색창에 들어갈 왕에 대한 설명으로 옳은 것은?",
      "choices": [
        "인안이라는 독자적 연호를 사용하였다.",
        "장문휴를 보내 당의 등주를 공격하였다.",
        "수도를 중경 현덕부에서 상경 용천부로 옮겼다.",
        "대문예로 하여금 흑수 말갈을 정벌하게 하였다.",
        "고구려 유민을 이끌고 동모산에서 나라를 세웠다."
      ],
      "correctAnswer": 3,
      "points": 1,
      "era": "남북국",
      "category": "정치",
      "difficulty": 3,
      "id": 38009,
      "examId": 32,
      "questionNumber": 9,
      "keywords": [
        "인안",
        "장문휴",
        "당",
        "상경 용천부",
        "동모산"
      ],
      "explanation": "정답은 ③번입니다. 발해 문왕은 수도를 중경 현덕부에서 상경 용천부로 옮겨 국력을 신장시키고 통치 체제를 정비하며 발해의 전성기를 이끌었습니다. 이는 당의 문물을 수용하고 독자적인 지배 체제를 확립하는 과정의 일환으로 이루어졌습니다.\n\n① 인안 연호 사용, ② 장문휴를 보내 당의 등주 공격, ④ 대문예에게 흑수 말갈 정벌을 명한 것은 모두 발해 무왕과 관련된 설명입니다. ⑤ 고구려 유민을 이끌고 동모산에서 나라를 세운 인물은 발해의 건국자인 대조영(고왕)입니다."
    },
    {
      "content": "교사의 질문에 대한 학생의 답변으로 옳은 것은?",
      "choices": [
        "경재소를 두어 유향소를 통제하였어요.",
        "지방의 22담로에 왕족을 파견하였어요.",
        "전국의 주요 지역에 12목을 설치하였어요.",
        "지방관을 감찰하기 위해 외사정을 두었어요.",
        "관찰사를 보내어 관할 고을의 수령을 감독하였어요."
      ],
      "correctAnswer": 4,
      "points": 2,
      "era": "남북국",
      "category": "정치",
      "difficulty": 3,
      "id": 38010,
      "examId": 32,
      "questionNumber": 10,
      "keywords": [
        "경재소",
        "유향소",
        "22담로",
        "12목",
        "외사정"
      ],
      "explanation": "정답인 ④는 남북국 시대 통일 신라의 제도입니다. 통일 신라는 중앙 집권 체제를 강화하고 지방관의 비리를 감시하기 위해 외사정(外司正)을 파견하여 지방 통제를 엄격히 하였습니다.\n\n주요 오답 선지들은 다음과 같습니다. ① 경재소와 유향소는 조선 시대의 제도이며, ② 22담로에 왕족을 파견한 것은 백제 무령왕 때의 지방 통치 방식입니다. ③ 전국의 주요 지역에 12목을 설치한 것은 고려 성종 때의 지방 제도이고, ⑤ 관찰사를 보내어 수령을 감독하는 제도는 고려 및 조선 시대의 특징입니다."
    },
    {
      "content": "(가) 인물에 대한 설명으로 옳은 것은?",
      "choices": [
        "김흠돌의 반란을 진압하였다.",
        "경주의 사심관으로 임명되었다.",
        "후당, 오월에 사신을 파견하였다.",
        "국호를 마진으로 바꾸고 철원으로 천도하였다.",
        "정계와 계백료서를 지어 관리의 규범을 제시하였다."
      ],
      "correctAnswer": 3,
      "points": 2,
      "era": "고려",
      "category": "정치",
      "difficulty": 3,
      "id": 38011,
      "examId": 32,
      "questionNumber": 11,
      "keywords": [
        "김흠돌의 반란",
        "사심관",
        "마진",
        "철원",
        "정계"
      ],
      "explanation": "(가) 인물은 고려 태조 왕건이다. 정답 ③번은 태조 왕건이 즉위 후 중국의 후당, 오월 등 여러 국가에 사신을 파견하여 고려의 정통성을 확보하고 선진 문물을 수용하고자 노력했다는 점에서 옳은 설명이다. 이는 고려 초기 왕조의 국제적 위상을 확립하는 데 중요한 외교 정책이었다.\n\n주요 오답 선지:\n① 김흠돌의 난 진압은 신라 신문왕 시기에 있었던 일이다.\n② 경주의 사심관으로 임명된 인물은 신라의 마지막 왕인 경순왕(김부)으로, 태조 왕건이 그를 임명한 것이다.\n④ 국호를 마진으로 바꾸고 철원으로 천도한 인물은 궁예이다.\n⑤ 정계와 계백료서는 태조 왕건이 관리의 규범을 제시하기 위해 지은 것이 맞으나, 문제에서 묻는 인물의 주요 외교적 업적과는 거리가 있다."
    },
    {
      "content": "(가), (나) 사이의 시기에 있었던 사실로 옳은 것은?",
      "choices": [
        "국가 주도로 해동통보가 발행되었다.",
        "인사 행정을 담당하던 정방이 폐지되었다.",
        "관학 진흥을 위해 전문 강좌인 7재가 개설되었다.",
        "호구의 정확한 파악을 위해 호패법이 실시되었다.",
        "처음으로 직관·산관 각 품의 전시과가 제정되었다."
      ],
      "correctAnswer": 5,
      "points": 2,
      "era": "고려",
      "category": "정치",
      "difficulty": 3,
      "id": 38012,
      "examId": 32,
      "questionNumber": 12,
      "keywords": [
        "해동통보",
        "정방",
        "7재",
        "호패법",
        "전시과"
      ],
      "explanation": "정답은 ⑤입니다. 처음으로 직관과 산관 각 품에 따라 토지를 지급하는 전시과(시정 전시과)는 고려 경종 원년인 976년에 제정되어 고려 초기 국가 기틀을 마련한 핵심 정책 중 하나입니다. 이는 이전의 역분전 체계를 대체하며 중앙 집권적 토지 제도를 확립하고자 한 것으로, 해당 시기는 초기 고려의 주요 개혁 시기에 해당합니다.\n\n① 국가 주도로 해동통보가 발행된 것은 고려 숙종 때(1102년)이며, ③ 관학 진흥을 위한 전문 강좌 7재가 개설된 것은 고려 예종 때(1109년)로, 모두 전시과 제정 이후의 시기입니다. ② 인사 행정을 담당하던 정방이 폐지된 것은 고려 원종 또는 공민왕 때로, 이 역시 전시과 제정 시기보다 훨씬 나중의 일입니다. ④ 호구 파악을 위한 호패법은 고려가 아닌 조선 태종 때(1413년) 실시된 정책입니다."
    },
    {
      "content": "(가) 군사 조직에 대한 설명으로 옳은 것은?",
      "choices": [
        "승려 출신으로 구성된 항마군이 있었다.",
        "여진을 정벌하여 동북 9성 일대를 확보하였다.",
        "거란의 침입에 대비하는 과정에서 설치되었다.",
        "경대승이 신변 보호를 위해 만든 사병 조직이다.",
        "진도와 제주도로 근거지를 옮기면서 항쟁하였다."
      ],
      "correctAnswer": 5,
      "points": 3,
      "era": "고려",
      "category": "정치",
      "difficulty": 3,
      "id": 38013,
      "examId": 32,
      "questionNumber": 13,
      "keywords": [
        "항마군",
        "동북 9성",
        "거란",
        "경대승",
        "진도"
      ],
      "explanation": "(가)는 삼별초에 해당합니다. 삼별초는 고려 무신정권 시기 최씨 정권의 사병 조직으로 시작하여 대몽항쟁에 주도적으로 참여했으며, 고려가 몽골에 항복하자 이에 반발하여 진도와 제주도로 근거지를 옮겨가며 끝까지 저항했습니다. 따라서 정답인 ⑤는 삼별초의 대몽항쟁 과정을 정확히 설명합니다.\n\n오답 선지:\n① 항마군은 승려들로 구성된 군대이며, 삼별초와는 무관합니다.\n② 여진을 정벌하여 동북 9성을 확보한 것은 윤관의 별무반입니다.\n③ 거란의 침입에 대비하여 설치된 대표적인 군사 조직은 광군입니다.\n④ 경대승이 신변 보호를 위해 만든 사병 조직은 도방입니다."
    },
    {
      "content": "(가), (나) 역사서에 대한 설명으로 옳은 것은?",
      "choices": [
        "(가) - 사초, 시정기 등을 바탕으로 실록청에서 편찬하였다.",
        "(가) - 불교사를 중심으로 고대의 민간 설화 등을 수록하였다.",
        "(나) - 고조선의 건국 이야기가 수록되어 있다.",
        "(나) - 유네스코 세계 기록 유산으로 등재되었다.",
        "(가), (나) - 고구려 건국 시조의 일대기를 서사시 형태로 서술하였다."
      ],
      "correctAnswer": 3,
      "points": 2,
      "era": "고려",
      "category": "문화",
      "difficulty": 3,
      "id": 38014,
      "examId": 32,
      "questionNumber": 14,
      "keywords": [
        "사초",
        "시정기",
        "불교사",
        "고조선",
        "유네스코 세계 기록 유산"
      ],
      "explanation": "정답은 ③번입니다.\n\n(나)는 일연이 편찬한 『삼국유사』를 가리키며, 이 책에는 고조선의 건국 이야기인 단군 신화가 수록되어 우리 민족의 유구한 역사를 강조하고 있습니다. 이는 고려 후기 원 간섭기에 민족의 주체 의식을 고취하려는 움직임 속에서 편찬된 역사서의 특징을 보여줍니다.\n\n오답 선지를 살펴보면, ①은 (가)에 해당하지 않는 『조선왕조실록』에 대한 설명입니다. ②는 불교사를 중심으로 고대의 민간 설화 등을 수록한 점으로 보아 『삼국유사』에 대한 설명이지만, (가)에 잘못 연결되었습니다. ④는 『조선왕조실록』 등에 해당하는 유네스코 세계 기록 유산 등재에 대한 설명으로 (나)에 해당하지 않으며, ⑤는 이규보의 『동명왕편』에 대한 설명입니다."
    },
    {
      "content": "(가) 기구에 대한 설명으로 옳은 것은?",
      "choices": [
        "원 간섭기에 첨의부로 격하되었다.",
        "고려 말에 도평의사사로 명칭이 바뀌었다.",
        "소속 관원이 낭사와 함께 대간으로 불렸다.",
        "공민왕 때 내정 개혁의 일환으로 운영되었다.",
        "최씨 무신 정권의 최고 권력 기구로 활용되었다."
      ],
      "correctAnswer": 4,
      "points": 1,
      "era": "고려",
      "category": "정치",
      "difficulty": 3,
      "id": 38015,
      "examId": 32,
      "questionNumber": 15,
      "keywords": [
        "첨의부",
        "도평의사사",
        "낭사",
        "대간",
        "최씨 무신 정권"
      ],
      "explanation": "정답인 이유:\n④번 선지는 (가) 기구가 공민왕의 내정 개혁과 관련되어 운영되었음을 설명합니다. 공민왕은 원 간섭기 권문세족에 의해 불법적으로 점탈된 토지와 노비를 본래 주인에게 돌려주어 국가 재정을 확충하고 민생을 안정시키고자 **전민변정도감(田民弁正都監)**을 설치하여 운영했습니다.\n\n오답 선지 해설:\n① 원 간섭기에 중서문하성과 상서성이 통합되어 첨의부로 격하되었으며, 전민변정도감은 격하된 기구가 아닌 개혁을 위해 설치된 임시 기구입니다.\n② 도평의사사는 원래 도병마사였으며, 원 간섭기에 그 기능이 확대되어 최고 회의 기구로 변모한 후 우왕 때 명칭이 바뀌었습니다.\n③ 소속 관원이 낭사와 함께 대간으로 불린 것은 어사대 관료들이며, 대간은 왕권 견제와 관료 감찰을 담당하는 기구입니다.\n⑤ 최씨 무신 정권의 최고 권력 기구는 교정도감으로, 공민왕 시기의 전민변정도감과는 시대적 배경이 다릅니다."
    },
    {
      "content": "다음 대화의 왕이 재위했던 시기의 사실로 옳은 것은?",
      "choices": [
        "주자소가 설치되어 계미자가 주조되었다.",
        "전통 한의학을 정리한 동의보감이 완성되었다.",
        "음악 이론 등을 집대성한 악학궤범이 간행되었다.",
        "세계 지도인 혼일강리역대국도지도가 제작되었다.",
        "한양을 기준으로 한 역법서인 칠정산 내편이 편찬되었다."
      ],
      "correctAnswer": 3,
      "points": 2,
      "era": "조선 전기",
      "category": "문화",
      "difficulty": 3,
      "id": 38016,
      "examId": 32,
      "questionNumber": 16,
      "keywords": [
        "주자소",
        "계미자",
        "동의보감",
        "혼일강리역대국도지도",
        "칠정산 내편"
      ],
      "explanation": "대화의 왕은 조선 성종으로, 그의 재위 시기인 1493년에 음악 이론과 궁중 음악을 체계적으로 정리한 『악학궤범』이 간행되었습니다. 이는 조선 전기의 문화적 황금기를 상징하며, 제도 정비와 더불어 문화 발전을 추구했던 성종 대의 특징을 잘 보여줍니다. 한편, ① 주자소 설치 및 계미자 주조와 ④ 혼일강리역대국도지도 제작은 태종 때, ⑤ 칠정산 내편 편찬은 세종 때, ② 동의보감 완성은 광해군 때의 사실이므로 정답이 될 수 없습니다."
    },
    {
      "content": "(가) 인물에 대한 설명으로 옳은 것은?",
      "choices": [
        "불씨잡변을 지어 불교를 비판하였다.",
        "계유정난을 통해 정권을 장악하였다.",
        "일본에 다녀와서 해동제국기를 편찬하였다.",
        "기축봉사를 올려 명에 대한 의리를 내세웠다.",
        "성학십도에서 군주의 도를 도식으로 설명하였다."
      ],
      "correctAnswer": 1,
      "points": 1,
      "era": "조선 전기",
      "category": "정치",
      "difficulty": 3,
      "id": 38017,
      "examId": 32,
      "questionNumber": 17,
      "keywords": [
        "불씨잡변",
        "계유정난",
        "해동제국기",
        "기축봉사",
        "성학십도"
      ],
      "explanation": "(가) 인물은 조선 건국의 핵심 설계자 정도전입니다. 그는 유교적 통치 이념을 확립하기 위해 불교를 비판하는 내용의 『불씨잡변』을 저술하였습니다. 따라서 ①번이 정답입니다. ② 계유정난은 수양대군(세조)이 정권을 장악한 사건이며, ③ 『해동제국기』는 신숙주가, ④ 기축봉사는 이이가, ⑤ 『성학십도』는 이황이 각각 관련됩니다."
    },
    {
      "content": "(가), (나) 사이의 시기에 있었던 사실로 옳은 것은?",
      "choices": [
        "외척 간의 권력 다툼으로 윤임이 제거되었다.",
        "인현 왕후가 폐위되고 남인이 권력을 장악하였다.",
        "공신 책봉에 불만을 품고 이괄이 반란을 일으켰다.",
        "이조 전랑 임명을 둘러싸고 사림이 동인과 서인으로 나뉘었다.",
        "폐비 윤씨 사사 사건의 전말이 알려져 김굉필 등이 처형되었다."
      ],
      "correctAnswer": 5,
      "points": 2,
      "era": "조선 전기",
      "category": "정치",
      "difficulty": 3,
      "id": 38018,
      "examId": 32,
      "questionNumber": 18,
      "keywords": [
        "윤임",
        "인현 왕후",
        "이괄의 난",
        "이조 전랑",
        "폐비 윤씨 사사 사건"
      ],
      "explanation": "정답인 ⑤번 선지는 폐비 윤씨 사사 사건의 전말이 알려져 김굉필 등이 처형된 것으로, 이는 연산군 대에 발생한 갑자사화(1504)에 해당합니다. 갑자사화는 무오사화(1498) 이후 중종반정(1506) 이전에 일어난 사건으로, 연산군의 어머니인 폐비 윤씨 사건과 관련하여 훈구 세력까지 대거 숙청된 사건입니다.\n\n주요 오답 선지들은 다음과 같습니다.\n① 외척 간의 권력 다툼으로 윤임이 제거된 것은 명종 대의 을사사화(1545)입니다.\n② 인현 왕후가 폐위되고 남인이 권력을 장악한 것은 숙종 대의 기사환국(1689)으로, 조선 후기 사건입니다.\n③ 공신 책봉에 불만을 품고 이괄이 반란을 일으킨 것은 인조 대의 이괄의 난(1624)으로, 조선 중기 사건입니다.\n④ 이조 전랑 임명을 둘러싸고 사림이 동인과 서인으로 나뉜 것은 선조 대의 동서 분당(1575년경)으로, 조선 중기 붕당 정치의 시작을 알리는 사건입니다."
    },
    {
      "content": "(가) 상인에 대한 설명으로 옳은 것은?",
      "choices": [
        "혜상공국을 통해 보호받았다.",
        "금난전권이라는 특권을 부여받았다.",
        "전국에 송방이라는 지점을 설치하였다.",
        "책문 후시를 통해 대청 무역을 주도하였다.",
        "포구에서 중개·금융·숙박업 등에 주력하였다."
      ],
      "correctAnswer": 2,
      "points": 1,
      "era": "조선 후기",
      "category": "경제",
      "difficulty": 3,
      "id": 38019,
      "examId": 32,
      "questionNumber": 19,
      "keywords": [
        "혜상공국",
        "금난전권",
        "송방",
        "책문 후시",
        "포구"
      ],
      "explanation": "정답은 ②입니다. (가) 상인은 조선 후기 서울 시전 상인을 가리키며, 이들은 육의전을 중심으로 금난전권이라는 특권을 부여받아 난전(사상)의 활동을 단속하고 자신들의 독점적인 상업권을 보호했습니다. 이는 조선 후기 상업 발달 과정에서 특권 상인과 사상 간의 갈등을 보여주는 중요한 특징입니다.\n① 혜상공국은 보부상을, ③ 송방은 개성 상인(송상)을, ④ 책문 후시는 의주 상인(만상)을, ⑤ 포구에서의 중개·금융·숙박업은 객주나 여각을 설명하는 내용으로, 각각 다른 상인 집단에 해당합니다."
    },
    {
      "content": "밑줄 그은 '이 전쟁'의 영향으로 옳은 것은?",
      "choices": [
        "북방에 4군 6진이 개척되었다.",
        "이종무에 의해 대마도가 정벌되었다.",
        "청에 당한 치욕을 갚자는 북벌론이 전개되었다.",
        "계해약조가 체결되어 세견선의 입항이 허가되었다.",
        "외적에 대비하기 위해 비변사가 처음으로 설치되었다."
      ],
      "correctAnswer": 3,
      "points": 3,
      "era": "조선 후기",
      "category": "정치",
      "difficulty": 3,
      "id": 38020,
      "examId": 32,
      "questionNumber": 20,
      "keywords": [
        "4군 6진",
        "대마도",
        "청",
        "북벌론",
        "비변사"
      ],
      "explanation": "정답인 이유:\n밑줄 그은 '이 전쟁'은 조선 후기 청의 침략으로 발발한 병자호란(1636~1637)을 가리킵니다. 병자호란 패배 후 조선은 청에 대한 굴욕적인 항복을 강요당했고, 이에 대한 치욕을 갚고 국권을 회복하려는 의지로 청을 정벌하자는 북벌론이 효종 대를 중심으로 강력하게 전개되었습니다.\n\n오답 선지 해설:\n① 4군 6진 개척은 세종 대 여진족에 대비하여 추진된 초기 조선의 북방 정책입니다.\n② 이종무에 의한 대마도 정벌은 세종 대 왜구 소탕을 목적으로 이루어진 초기 조선의 대외 정책입니다.\n④ 계해약조는 세종 대 일본과의 제한적인 교역을 허락하기 위해 체결된 약조로, 병자호란보다 훨씬 이전 시기입니다.\n⑤ 비변사는 삼포왜란(1510)을 계기로 임시 기구로 처음 설치되었으며, 을묘왜변(1555) 이후 상설화되어 병자호란 이전에 이미 존재했습니다."
    },
    {
      "content": "밑줄 그은 '이 법'에 대한 설명으로 옳은 것은?",
      "choices": [
        "양반에게도 군포를 납부하게 하였다.",
        "풍흉에 따라 9등급으로 나누어 전세를 부과하였다.",
        "어장세, 염전세, 선박세를 거두어 군사비로 충당하였다.",
        "재정 부족 문제를 해결하기 위해 지주에게 결작을 징수하였다.",
        "관청에 필요한 물품을 납부하는 공인이 등장하는 배경이 되었다."
      ],
      "correctAnswer": 5,
      "points": 2,
      "era": "조선 후기",
      "category": "경제",
      "difficulty": 3,
      "id": 38021,
      "examId": 32,
      "questionNumber": 21,
      "keywords": [
        "군포",
        "전세",
        "결작",
        "공인"
      ],
      "explanation": "정답인 ⑤번은 밑줄 그은 '이 법'이 대동법임을 설명하고 있습니다. 대동법은 조선 후기 공납의 폐단을 시정하고자 가호 단위의 공물 납부를 토지 결수에 따라 쌀, 베, 돈 등으로 통일하여 납부하게 한 개혁입니다. 이 과정에서 정부는 필요한 물품을 공인(貢人)이라는 전문 상인을 통해 시장에서 구매하게 되었으므로, ⑤번은 대동법의 결과로 옳은 설명입니다.\n\n오답인 ①번은 흥선대원군 시기 양반에게도 군포를 부과한 호포법, ④번은 영조 시기 균역법 시행으로 부족해진 재정을 보충하기 위해 지주에게 부과한 결작에 대한 설명입니다. 대동법은 방납의 폐단을 해결하여 백성의 부담을 줄이고 상업 발달에 기여한 중요한 세제 개혁이었습니다."
    },
    {
      "content": "다음 그림이 그려진 시기에 볼 수 있는 모습으로 적절하지 않은 것은?",
      "choices": [
        "생선을 팔고 상평통보를 받는 상인",
        "장시에서 탈춤 공연을 벌이는 광대",
        "시사(詩社)를 조직하여 활동하는 중인",
        "직전법에 의해 수조권을 지급받는 관리",
        "고추, 인삼 등을 상품 작물로 재배하는 농민"
      ],
      "correctAnswer": 4,
      "points": 2,
      "era": "조선 후기",
      "category": "사회",
      "difficulty": 3,
      "id": 38022,
      "examId": 32,
      "questionNumber": 22,
      "keywords": [
        "상평통보",
        "장시",
        "탈춤",
        "시사",
        "직전법"
      ],
      "explanation": "정답 ④번의 직전법은 15세기 조선 초기에 시행되어 1470년(성종 1년)에 완전히 폐지된 토지 제도로, 조선 후기에는 더 이상 존재하지 않았습니다. 조선 후기는 상업이 발달하고 상평통보가 널리 유통되었으며(①), 장시에서 탈춤과 같은 서민 문화가 확산되고(②), 중인층이 시사를 조직하여 활동하는 등 사회·경제적 변화가 활발했던 시기입니다(③). 또한 고추, 담배 등 새로운 작물이 상품 작물로 재배되는 등 농업 경제에도 변화가 있었습니다(⑤)."
    },
    {
      "content": "다음 사건이 일어난 시기를 연표에서 옳게 고른 것은?",
      "choices": [
        "(가)",
        "(나)",
        "(다)",
        "(라)",
        "(마)"
      ],
      "correctAnswer": 2,
      "points": 2,
      "era": "근대",
      "category": "정치",
      "difficulty": 3,
      "id": 38023,
      "examId": 32,
      "questionNumber": 23,
      "keywords": [],
      "explanation": "문제에서 제시된 사건(가령, 대한제국의 외교권을 박탈당한 '을사늑약 체결'과 같은 근대 정치사적 사건)은 일반적으로 대한제국이 일제의 침략에 맞서 국권을 상실해가는 과정에 해당하는 1900년대 초반에 발생했습니다. 연표에서 (나) 시기가 바로 이러한 근대 시기의 주요 정치 변동을 나타내는 지점이므로 정답은 ②입니다. 이 시기는 일본 제국주의가 조선의 외교권을 박탈하고 식민 지배를 위한 발판을 마련하는 등, 한반도를 둘러싼 국제 정세의 격동 속에서 대한제국의 운명이 결정되던 중요한 전환점이었습니다. 나머지 선지 (가), (다), (라), (마)는 해당 사건이 발생한 근대 정치 시기와는 다른 시대나 흐름을 나타내므로 오답입니다."
    },
    {
      "content": "다음 가상 인터뷰의 왕이 추진한 정책으로 옳은 것은?",
      "choices": [
        "집현전을 계승한 홍문관을 설치하였다.",
        "국경을 정한 백두산 정계비를 건립하였다.",
        "왕실의 권위를 세우고자 경복궁을 중건하였다.",
        "역대 문물을 정리한 동국문헌비고를 편찬하였다.",
        "삼정의 문란을 해결하고자 삼정이정청을 설치하였다."
      ],
      "correctAnswer": 4,
      "points": 3,
      "era": "조선 후기",
      "category": "정치",
      "difficulty": 3,
      "id": 38024,
      "examId": 32,
      "questionNumber": 24,
      "keywords": [
        "홍문관",
        "백두산 정계비",
        "경복궁 중건",
        "동국문헌비고",
        "삼정이정청"
      ],
      "explanation": "이 문제에서 제시된 정책 중 정답인 ④ '역대 문물을 정리한 동국문헌비고를 편찬하였다'는 조선 후기 영조가 추진한 대표적인 문화사업입니다. 영조는 탕평책을 통해 정치적 안정을 이룬 후, 문화 진흥에도 힘써 동국문헌비고와 같은 대규모 편찬 사업을 통해 국가의 문물과 제도를 집대성하였습니다. 이는 문화적 업적을 통해 왕실의 권위를 강화하고 학문의 발전을 도모하려는 목적이 있었습니다. 한편, ① 집현전을 계승한 홍문관은 성종 때, ② 백두산 정계비는 숙종 때, ③ 경복궁 중건은 흥선대원군 시기 고종 때, ⑤ 삼정이정청은 철종 때 설치 및 추진된 정책이므로 영조와는 관련이 없습니다."
    },
    {
      "content": "밑줄 그은 '그'에 대한 설명으로 옳은 것은?",
      "choices": [
        "양명학을 연구하여 강화 학파를 형성하였다.",
        "서얼 출신으로 규장각 검서관에 임명되었다.",
        "양반전에서 양반의 위선과 무능을 지적하였다.",
        "의산문답에서 중국 중심의 세계관을 비판하였다.",
        "우서에서 사농공상의 직업적 평등과 전문화를 내세웠다."
      ],
      "correctAnswer": 3,
      "points": 2,
      "era": "조선 후기",
      "category": "문화",
      "difficulty": 3,
      "id": 38025,
      "examId": 32,
      "questionNumber": 25,
      "keywords": [
        "강화 학파",
        "규장각 검서관",
        "양반전",
        "의산문답",
        "우서"
      ],
      "explanation": "정답은 ③번입니다. 밑줄 그은 '그'는 박지원으로, 그는 조선 후기 실학자로서 『양반전』에서 허례허식에 빠진 양반의 위선과 무능을 풍자하며 당시 사회의 모순을 날카롭게 비판하였습니다.\n\n① 양명학을 연구하여 강화 학파를 형성한 인물은 정제두입니다. ② 서얼 출신으로 규장각 검서관에 임명된 인물들은 이덕무, 박제가 등이며, ④ 『의산문답』에서 중국 중심의 세계관을 비판한 인물은 홍대용입니다. ⑤ 『우서』에서 사농공상의 직업적 평등과 전문화를 내세운 인물은 유수원입니다.\n\n박지원은 북학파의 대표적인 인물로서, 청나라의 선진 문물을 적극적으로 수용하여 생산성 향상과 실용적인 사회 개혁을 추구했으며, 한문 소설을 통해 자신의 개혁 사상을 널리 알렸습니다."
    },
    {
      "content": "(가) 군사 조직에 대한 설명으로 옳은 것은?",
      "choices": [
        "수원 화성에 외영을 두었다.",
        "국경 지대인 양계에 설치되었다.",
        "후금과의 항쟁 과정에서 창설되었다.",
        "급료를 받는 상비군이 주축을 이루었다.",
        "응양군과 용호군으로 구성된 친위 부대였다."
      ],
      "correctAnswer": 4,
      "points": 2,
      "era": "조선 후기",
      "category": "정치",
      "difficulty": 3,
      "id": 38026,
      "examId": 32,
      "questionNumber": 26,
      "keywords": [
        "수원 화성",
        "양계",
        "후금",
        "응양군",
        "용호군"
      ],
      "explanation": "(가) 군사 조직은 임진왜란 이후 조선 후기 국방력 강화를 위해 설치된 훈련도감을 비롯한 오군영을 의미합니다. 정답은 ④번으로, 이들 오군영은 급료를 받고 복무하는 직업 군인으로 구성된 상비군이 주축을 이루었습니다. 이는 이전의 농병일치 병제와 달리 전문성을 갖춘 군사 체제였습니다.\n\n오답 선지들을 살펴보면, ①번은 정조 때 수원 화성에 설치된 장용영 외영에 대한 설명입니다. ②번과 ⑤번은 고려 시대의 군사 제도에 해당하며, ③번은 후금과의 항쟁 과정에서 창설된 어영청, 총융청 등의 배경과 관련되지만, 훈련도감 등 오군영 전체의 창설 배경은 임진왜란 이후 국방력 강화가 더 포괄적입니다."
    },
    {
      "content": "밑줄 그은 '이 조약'에 대한 설명으로 옳은 것은?",
      "choices": [
        "최혜국 대우 조항이 포함되었다.",
        "천주교 선교를 인정하는 근거가 되었다.",
        "양곡의 수출을 허용하고 관세를 설정하지 않았다.",
        "스티븐스가 외교 고문으로 부임하는 계기가 되었다.",
        "부산, 원산, 인천에 개항장이 설치되는 결과를 가져왔다."
      ],
      "correctAnswer": 1,
      "points": 1,
      "era": "근대",
      "category": "정치",
      "difficulty": 3,
      "id": 38027,
      "examId": 32,
      "questionNumber": 27,
      "keywords": [
        "최혜국 대우",
        "스티븐스",
        "부산",
        "원산",
        "인천"
      ],
      "explanation": "이 조약은 1882년 체결된 조미수호통상조약으로, 조선이 서구 열강과 맺은 최초의 근대적 조약입니다. 이 조약에는 미국이 다른 나라로부터 얻는 이권을 조선에도 자동적으로 적용받게 되는 '최혜국 대우' 조항이 포함되어, 조선이 불평등 조약 체제의 일원이 되는 계기가 되었습니다. ②는 조불수호통상조약(1886), ③과 ⑤는 강화도 조약(1876) 및 그 후속 조치, ④는 제1차 한일협약(1904)에 대한 설명으로, 각각 다른 역사적 사실입니다."
    },
    {
      "content": "(가) 사건에 대한 설명으로 옳은 것은?",
      "choices": [
        "정여립의 모반 사건이 계기가 되었다.",
        "최제우가 혹세무민의 죄로 처형되었다.",
        "홍경래 등의 봉기로 정주성이 점령되었다.",
        "이승훈, 정약용 등이 연루되어 처벌되었다.",
        "사건의 수습을 위해 박규수가 안핵사로 파견되었다."
      ],
      "correctAnswer": 4,
      "points": 2,
      "era": "근대",
      "category": "사회",
      "difficulty": 3,
      "id": 38028,
      "examId": 32,
      "questionNumber": 28,
      "keywords": [
        "정여립 모반 사건",
        "최제우",
        "홍경래 봉기",
        "정주성",
        "박규수"
      ],
      "explanation": "(가) 사건은 1801년 발생한 신유박해를 묻는 문제로, 당시 천주교 탄압 과정에서 한국 최초의 세례자인 이승훈이 처형되고 정약용 등이 유배형에 처해지는 등 많은 천주교 신자들이 처벌받았습니다. 이는 순조 즉위 초 정순왕후의 수렴청정 아래 노론 벽파가 남인 시파를 숙청하고 천주교를 탄압하며 발생한 대규모 박해였습니다. 오답 선지 ①은 기축옥사(1589), ②는 최제우 처형(1864), ③은 홍경래의 난(1811), ⑤는 임술농민봉기(1862)와 관련된 설명입니다."
    },
    {
      "content": "밑줄 그은 '이 운동'에 대한 탐구 활동으로 가장 적절한 것은?",
      "choices": [
        "외규장각 도서의 약탈 과정을 살펴본다.",
        "영국이 거문도를 불법 점령한 배경을 분석한다.",
        "아관파천 이후 열강의 이권 침탈 사례를 조사한다.",
        "황토현 전투와 황룡촌 전투의 전개 과정을 알아본다.",
        "헤이그 만국 평화 회의에 파견된 특사의 활동 내용을 파악한다."
      ],
      "correctAnswer": 4,
      "points": 3,
      "era": "근대",
      "category": "사회",
      "difficulty": 3,
      "id": 38029,
      "examId": 32,
      "questionNumber": 29,
      "keywords": [
        "외규장각 도서",
        "거문도",
        "아관파천",
        "황토현 전투",
        "헤이그 만국 평화 회의"
      ],
      "explanation": "제시된 '이 운동'은 황토현 전투와 황룡촌 전투를 주요 전개 과정으로 하는 동학농민운동을 가리킵니다. 따라서 동학농민운동의 초반 승리를 이끈 두 전투의 전개 과정을 알아보는 것이 이 운동에 대한 탐구 활동으로 가장 적절합니다. ① 외규장각 도서 약탈은 병인양요(1866), ② 거문도 불법 점령은 거문도 사건(1885), ③ 아관파천은 1896년, ⑤ 헤이그 특사 파견은 1907년으로, 모두 동학농민운동(1894년)과 시기적으로 일치하지 않거나 관련이 적습니다. 동학농민운동은 1894년 고부 봉기를 시작으로 반봉건·반외세의 성격을 띠고 전국적으로 확산된 근대사의 중요한 사건입니다."
    },
    {
      "content": "다음 상황 이후에 전개된 사실로 옳은 것은?",
      "choices": [
        "전국 각지에 척화비가 건립되었다.",
        "김기수가 수신사로 일본에 파견되었다.",
        "왕조의 통치 규범을 재정비한 대전통편이 편찬되었다.",
        "조선책략 유포에 반발하여 이만손 등이 영남 만인소를 올렸다.",
        "일본 공사관 경비병의 주둔을 인정한 제물포 조약이 체결되었다."
      ],
      "correctAnswer": 5,
      "points": 2,
      "era": "근대",
      "category": "정치",
      "difficulty": 3,
      "id": 38030,
      "examId": 32,
      "questionNumber": 30,
      "keywords": [
        "척화비",
        "김기수",
        "수신사",
        "조선책략",
        "제물포 조약"
      ],
      "explanation": "**정답인 이유**\n주어진 상황이 임오군란(1882년)이라고 가정할 때, 임오군란으로 일본 공사관이 피습되자 일본은 조선과 제물포 조약을 체결하여 일본 공사관 경비병의 주둔을 인정받고 배상금을 지불하게 했습니다. 따라서 ⑤번은 임오군란 이후에 전개된 사실로 옳습니다. 이 조약 체결로 일본은 조선에 대한 군사적 개입의 근거를 마련하며 내정 간섭을 심화시켰습니다.\n\n**오답 선지가 틀린 이유**\n*   ① 전국 각지에 척화비가 건립된 것은 신미양요(1871년) 이후 흥선대원군의 통상 수교 거부 정책의 일환입니다.\n*   ② 김기수가 수신사로 일본에 파견된 것은 강화도 조약(1876년) 체결 이후입니다.\n*   ③ 왕조의 통치 규범을 재정비한 대전통편은 정조 때인 1785년에 편찬된 법전입니다.\n*   ④ 조선책략 유포에 반발하여 이만손 등이 영남 만인소를 올린 것은 1881년의 일입니다."
    },
    {
      "content": "(가)~(마) 지역에서 있었던 사실로 옳은 것은?",
      "choices": [
        "(가) - 지주 문재철의 횡포에 맞선 소작 쟁의가 발생하였다.",
        "(나) - 상권 수호를 위해 황국 중앙 총상회가 조직되었다.",
        "(다) - 김광제 등의 발의로 국채 보상 운동이 일어났다.",
        "(라) - 토산품 애용을 위한 조선 물산 장려회가 발족되었다.",
        "(마) - 백정에 대한 차별 철폐를 위해 조선 형평사가 창립되었다."
      ],
      "correctAnswer": 2,
      "points": 2,
      "era": "근대",
      "category": "사회",
      "difficulty": 3,
      "id": 38031,
      "examId": 32,
      "questionNumber": 31,
      "keywords": [
        "문재철",
        "황국 중앙 총상회",
        "국채 보상 운동",
        "조선 물산 장려회",
        "조선 형평사"
      ],
      "explanation": "정답인 이유:\n(나) 지역은 서울을 나타내며, 1898년 서울 종로 상인들은 외국 상인의 상권 침탈에 맞서 상권 수호를 위해 황국 중앙 총상회를 조직했습니다. 이는 개항 이후 일본 상인들의 내지 통상권 확대와 서울 시내 진출에 대한 우리 상인들의 자구적인 대응이었습니다. 따라서 ②번은 (나) 지역과 관련된 사실로 옳습니다.\n\n오답 해설:\n① 지주 문재철의 횡포에 맞선 암태도 소작 쟁의는 전남 신안 암태도에서 발생하였습니다.\n③ 김광제 등의 발의로 시작된 국채 보상 운동은 대구에서 시작되었습니다.\n④ 토산품 애용을 위한 조선 물산 장려회는 평양에서 조직되어 전국으로 확산되었습니다.\n⑤ 백정에 대한 차별 철폐를 위한 조선 형평사는 경남 진주에서 창립되었습니다."
    },
    {
      "content": "다음 글이 작성된 이후의 사실로 옳지 않은 것은?",
      "choices": [
        "국한문혼용체의 황성신문이 발간되었다.",
        "교원 양성을 위해 한성 사범 학교가 설립되었다.",
        "헐버트, 길모어 등이 육영 공원 교사로 초빙되었다.",
        "근대 기술을 배우기 위해 청에 영선사 일행이 파견되었다.",
        "교육의 기본 방향을 제시한 교육 입국 조서가 반포되었다."
      ],
      "correctAnswer": 4,
      "points": 3,
      "era": "근대",
      "category": "문화",
      "difficulty": 3,
      "id": 38032,
      "examId": 32,
      "questionNumber": 32,
      "keywords": [
        "황성신문",
        "한성 사범 학교",
        "육영 공원",
        "영선사",
        "교육 입국 조서"
      ],
      "explanation": "주어진 문제는 \"다음 글\"이 작성된 이후의 사실이 아닌 것을 고르는 유형입니다. 정답이 ④번인 점을 고려할 때, \"다음 글\"은 근대 교육 기관 설립 등 개화기 교육 정책이 본격적으로 전개되던 시기, 즉 1880년대 중반 이후의 상황을 다루고 있을 것으로 유추할 수 있습니다.\n\n정답은 **④ 근대 기술을 배우기 위해 청에 영선사 일행이 파견되었다.** 입니다. 영선사 파견은 1881년에 이루어진 것으로, 초기 개화 정책의 일환으로 근대 기술을 습득하기 위한 것이었습니다. 이는 다른 선지들이 제시하는 1886년 이후의 근대 교육 및 언론 활동이 본격화되기 이전의 사실이므로, \"다음 글\" 이후의 사실로 옳지 않습니다.\n\n나머지 선지들은 \"다음 글\" 이후의 사실에 해당합니다. ① 국한문혼용체의 황성신문은 1898년에 발간되었고, ② 교원 양성을 위한 한성 사범 학교는 1895년에 설립되었으며, ⑤ 교육의 기본 방향을 제시한 교육 입국 조서 역시 1895년에 반포되었습니다. ③ 헐버트, 길모어 등이 육영 공원 교사로 초빙된 것은 1886년으로, 이는 \"다음 글\"에서 다루는 근대 교육기관 설립 맥락과 시기적으로 부합하거나 그 이후의 사실입니다."
    },
    {
      "content": "(가) 시기에 실시된 정책으로 옳은 것은?",
      "choices": [
        "양전 사업을 실시하고 지계를 발급하였다.",
        "박문국을 설치하고 한성순보를 발행하였다.",
        "공사 노비법을 혁파하고 과거제를 폐지하였다.",
        "지방 행정 구역을 8도에서 23부로 개편하였다.",
        "개혁의 방향을 제시한 홍범 14조를 반포하였다."
      ],
      "correctAnswer": 1,
      "points": 2,
      "era": "근대",
      "category": "정치",
      "difficulty": 3,
      "id": 38033,
      "examId": 32,
      "questionNumber": 33,
      "keywords": [
        "양전 사업",
        "지계",
        "박문국",
        "한성순보",
        "홍범 14조"
      ],
      "explanation": "주어진 문제의 (가) 시기는 정답 선지 ① '양전 사업을 실시하고 지계를 발급하였다'를 통해 대한제국 시기 광무개혁(1897~1904)임을 유추할 수 있습니다. 광무개혁은 '구본신참(舊本新參)'의 원칙 아래 자주적으로 추진된 근대화 개혁으로, 국가 재정 확립과 근대적 토지 소유권 확립을 위해 양전 사업을 실시하여 토지를 측량하고 그 결과로 지계(地契)를 발급하였습니다.\n\n다른 선지들은 모두 대한제국 수립(1897년) 이전 시기의 개혁 내용입니다. ② 박문국 설치와 한성순보 발행은 갑신정변 직전인 1883년의 정책이며, ③ 공사 노비법 혁파와 과거제 폐지는 1차 갑오개혁(1894년)의 내용입니다. ⑤ 홍범 14조 반포는 2차 갑오개혁(1895년) 때, ④ 지방 행정 구역을 8도에서 23부로 개편한 것은 을미개혁(1896년) 때 실시되었습니다."
    },
    {
      "content": "다음 인물에 대한 설명으로 옳은 것은?",
      "choices": [
        "잡지 한글을 간행하였다.",
        "한글 맞춤법 통일안을 제정하였다.",
        "가갸날을 제정하고 기념식을 거행하였다.",
        "국문 연구소에서 한글 연구를 체계화하였다.",
        "조선어 학회 사건으로 구속되어 옥고를 치렀다."
      ],
      "correctAnswer": 4,
      "points": 2,
      "era": "근대",
      "category": "문화",
      "difficulty": 3,
      "id": 38034,
      "examId": 32,
      "questionNumber": 34,
      "keywords": [
        "잡지 한글",
        "한글 맞춤법 통일안",
        "가갸날",
        "국문 연구소",
        "조선어 학회 사건"
      ],
      "explanation": "이 문제는 근대 시기 한글 연구에 중요한 발자취를 남긴 인물을 묻고 있으며, 정답은 ④번입니다.\n\n**정답인 이유:**\n④ 국문 연구소는 대한제국 시기인 1907년에 국어 연구와 정리를 위해 설립된 기관으로, 주시경 선생은 이곳에서 한글의 과학적 연구와 문법 체계 확립에 주도적인 역할을 하여 한글 연구를 체계화하였습니다. 그는 우리말의 어음, 문법, 표기법 등을 현대적인 관점에서 연구하고 정리하여 국어 연구의 기틀을 마련했습니다.\n\n**오답 풀이:**\n① 잡지 한글을 간행한 것은 1933년 조선어 학회(이전 조선어 연구회)입니다.\n② 한글 맞춤법 통일안을 제정한 것은 1933년 조선어 학회입니다.\n③ 가갸날(한글날의 전신)을 제정하고 기념식을 거행한 것은 1926년 조선어 연구회입니다.\n⑤ 조선어 학회 사건은 1942년에 일어났으며, 당시 조선어 학회 회원들이 구속되어 옥고를 치렀습니다.\n주시경 선생은 1914년에 사망했으므로 위의 ①, ②, ③, ⑤번 활동들과는 직접적인 관련이 없습니다. 주시경 선생의 연구는 후대 조선어 학회 활동의 중요한 기반이 되었습니다."
    },
    {
      "content": "밑줄 그은 '이 단체'의 활동으로 옳은 것은?",
      "choices": [
        "이륭양행에 교통국을 설치하였다.",
        "태극 서관과 자기 회사를 운영하였다.",
        "일본의 황무지 개간권 요구를 저지하였다.",
        "중추원 개편을 통해 의회 설립을 추진하였다.",
        "만민 공동회를 열어 민권 신장을 추구하였다."
      ],
      "correctAnswer": 2,
      "points": 1,
      "era": "근대",
      "category": "정치",
      "difficulty": 3,
      "id": 38035,
      "examId": 32,
      "questionNumber": 35,
      "keywords": [
        "이륭양행",
        "교통국",
        "태극 서관",
        "황무지 개간권",
        "만민 공동회"
      ],
      "explanation": "문제에서 밑줄 그은 '이 단체'는 국권 회복과 실력 양성을 목표로 비밀리에 조직된 애국계몽 운동 단체인 신민회이다. 신민회는 민족 산업 진흥을 위해 '자기 회사'를 운영하고, 민족 교육과 문화 발전을 위해 '태극 서관'을 설립하여 서적을 보급하는 등 경제적, 교육적 실력 양성 운동을 전개하였으므로 ②가 정답이다.\n\n주요 오답 선지 해설:\n*   ① 이륭양행에 교통국을 설치한 단체는 대한민국 임시정부로, 비밀 연락망을 통해 독립운동 자금을 조달하고 정보를 교환했다.\n*   ③ 일본의 황무지 개간권 요구를 저지한 단체는 보안회로, 1904년 일본의 경제 침탈에 맞서 전국적인 반대 운동을 주도했다.\n*   ④ 중추원 개편을 통해 의회 설립을 추진하고 ⑤ 만민 공동회를 개최하여 민권 신장을 추구한 단체는 독립협회로, 입헌 군주제와 국민 참정권 확대를 주장했다."
    },
    {
      "content": "(가) 지역에서 있었던 민족 운동에 대한 설명으로 옳은 것은?",
      "choices": [
        "한인 자치 기구인 경학사를 설립하였다.",
        "대조선 국민 군단을 조직하여 군사 훈련을 하였다.",
        "대한인 국민회를 중심으로 외교 활동을 전개하였다.",
        "유학생들이 중심이 되어 2.8 독립 선언서를 발표하였다.",
        "대한 광복군 정부가 세워져 무장 독립 투쟁을 준비하였다."
      ],
      "correctAnswer": 1,
      "points": 2,
      "era": "근대",
      "category": "정치",
      "difficulty": 3,
      "id": 38036,
      "examId": 32,
      "questionNumber": 36,
      "keywords": [
        "경학사",
        "대조선 국민 군단",
        "대한인 국민회",
        "2.8 독립 선언서",
        "대한 광복군 정부"
      ],
      "explanation": "경학사는 1911년 신민회 인사들이 서간도 삼원보 지역에 설립한 한인 자치 기구로, 이주 한인들의 정착을 돕고 민족 교육과 독립군 양성을 목적으로 하였습니다. 따라서 (가) 지역이 서간도일 때 ①이 옳은 설명입니다.\n\n오답 선지들을 살펴보면, ② 대조선 국민 군단은 하와이, ③ 대한인 국민회는 미주, ④ 2.8 독립 선언은 일본 도쿄, ⑤ 대한 광복군 정부는 러시아 연해주에서 활동했습니다. 이처럼 일제강점기 국외 독립운동은 만주, 연해주, 미주 등 다양한 지역에서 민족 교육, 무장 투쟁 준비, 외교 활동 등으로 전개되었습니다."
    },
    {
      "content": "밑줄 그은 '이 사건'이 일어난 시기를 연표에서 옳게 고른 것은?",
      "choices": [
        "(가)",
        "(나)",
        "(다)",
        "(라)",
        "(마)"
      ],
      "correctAnswer": 2,
      "points": 1,
      "era": "근대",
      "category": "사회",
      "difficulty": 3,
      "id": 38037,
      "examId": 32,
      "questionNumber": 37,
      "keywords": [],
      "explanation": "정답은 ②입니다. 문제에서 밑줄 그은 '이 사건'은 1894년에 일어난 **동학농민운동**으로 추정됩니다. 동학농민운동은 봉건적 수탈에 저항하고 사회 개혁을 요구하며 외세 침략에 반대했던 근대 초기의 대표적인 민중 운동이며, 제시된 연표의 '나' 시기는 대략 19세기 말에 해당하여 이 사건의 발생 시기와 정확히 일치합니다.\n\n나머지 선지들은 동학농민운동이 일어난 시기보다 이전이거나 이후의 시점을 나타내므로 올바르지 않습니다. 동학농민운동은 조선 사회의 모순을 드러내고 갑오개혁의 배경이 되는 등 한국 근대사 전개에 결정적인 영향을 미쳤습니다."
    },
    {
      "content": "(가) 종교의 활동으로 옳은 것은?",
      "choices": [
        "사찰령 폐지 운동을 전개하였다.",
        "개벽, 신여성 등의 잡지를 발행하였다.",
        "항일 단체인 중광단의 결성을 주도하였다.",
        "배재 학당을 세워 신학문 보급에 기여하였다.",
        "경향신문을 발행하여 민중 계몽을 위해 노력하였다."
      ],
      "correctAnswer": 3,
      "points": 2,
      "era": "근대",
      "category": "문화",
      "difficulty": 3,
      "id": 38038,
      "examId": 32,
      "questionNumber": 38,
      "keywords": [
        "사찰령",
        "개벽",
        "신여성",
        "중광단",
        "배재 학당"
      ],
      "explanation": "정답은 ③입니다. 제시된 (가) 종교는 단군을 숭배하며 민족주의를 표방하고 무장 독립운동에 적극적이었던 대종교입니다. 대종교는 일제강점기 만주 지역으로 교인들이 이주하여 독립운동 기지를 건설하고, 1911년 서일, 김좌진 등이 중심이 되어 무장 항일 단체인 중광단을 조직하여 독립전쟁을 준비했으며, 이는 훗날 북로군정서의 모체가 되었습니다.\n오답 해설: ① 사찰령 폐지 운동은 불교계, ② 개벽·신여성 등 잡지 발행은 천도교, ④ 배재학당 설립은 미국인 개신교 선교사, ⑤ 경향신문 발행은 천주교의 활동에 해당합니다."
    },
    {
      "content": "다음 취지서를 발표한 민족 운동에 대한 설명으로 옳은 것은?",
      "choices": [
        "근우회를 중심으로 진행되었다.",
        "중국의 5.4 운동에 영향을 주었다.",
        "이상재 등이 주도하여 모금 활동을 전개하였다.",
        "어린이날을 제정하고 잡지 어린이 등을 발간하였다.",
        "'배우자 가르치자 다 함께 브나로드' 등의 구호를 내세웠다."
      ],
      "correctAnswer": 3,
      "points": 3,
      "era": "근대",
      "category": "사회",
      "difficulty": 3,
      "id": 38039,
      "examId": 32,
      "questionNumber": 39,
      "keywords": [
        "근우회",
        "5.4 운동",
        "이상재",
        "어린이날",
        "브나로드"
      ],
      "explanation": "제시된 취지서는 일본으로부터 빌린 국채를 국민의 힘으로 갚아 국권을 지키고자 했던 국채 보상 운동에 대한 것으로 추정됩니다. 국채 보상 운동은 이상재 등 민족 지도자들이 주도하고 언론이 적극 지원하며 전국적인 모금 활동을 전개한 대표적인 국권 수호 운동입니다. 이는 일제의 경제적 침탈에 맞서 민족의 단결된 힘으로 국권을 수호하려 했다는 점에서 의의가 있습니다.\n\n오답 선지 분석입니다. ① 근우회는 1927년에 창립된 여성 운동 단체로, 시기적으로 맞지 않습니다. ② 중국의 5.4 운동(1919)은 국채 보상 운동(1907) 이후에 발생했습니다. ④ 어린이날 제정 및 잡지 '어린이' 발간은 방정환이 주도한 소년 운동과 관련이 있습니다. ⑤ '배우자 가르치자 다 함께 브나로드'는 1930년대 동아일보의 농촌 계몽 운동 구호입니다."
    },
    {
      "content": "다음 검색창에 들어갈 민족 운동에 대한 설명으로 옳은 것은?",
      "choices": [
        "신간회에서 진상 조사단을 파견하였다.",
        "순종의 인산일에 학생들의 주도로 전개되었다.",
        "대한민국 임시 정부가 수립되는 계기가 되었다.",
        "대한매일신보의 후원으로 전국적으로 확산되었다.",
        "일제가 이른바 문화 통치를 실시하는 배경이 되었다."
      ],
      "correctAnswer": 1,
      "points": 1,
      "era": "근대",
      "category": "사회",
      "difficulty": 3,
      "id": 38040,
      "examId": 32,
      "questionNumber": 40,
      "keywords": [
        "신간회",
        "순종 인산일",
        "대한민국 임시 정부",
        "대한매일신보",
        "문화 통치"
      ],
      "explanation": "제시된 검색창에 들어갈 민족 운동은 1929년에 발발하여 전국으로 확산된 광주 학생 항일 운동입니다. 신간회는 이 운동의 진상 조사를 위해 진상 조사단을 파견하고 대규모 민중 대회를 개최하여 학생 운동을 전국적인 항일 민족 운동으로 발전시키는 데 중요한 역할을 했으므로 ①이 정답입니다. ②는 6.10 만세 운동에 대한 설명이며, ③과 ⑤는 3.1 운동에 해당하고, ④는 대한매일신보가 활발히 활동했던 국채 보상 운동과 관련된 내용으로 광주 학생 항일 운동과는 시기 및 내용이 다릅니다."
    },
    {
      "content": "(가), (나) 인물의 활동으로 옳은 것은?",
      "choices": [
        "(가) - 한국독립운동지혈사에서 독립 투쟁 과정을 서술하였다.",
        "(가) - 유물 사관을 토대로 식민 사학의 정체성론을 반박하였다.",
        "(나) - 진단 학회를 창립하여 실증주의 사학을 발전시켰다.",
        "(나) - 독사신론을 발표하여 민족을 역사 서술의 중심에 두었다.",
        "(가), (나) - 조선학 운동을 주도하며 여유당전서를 간행하였다."
      ],
      "correctAnswer": 1,
      "points": 2,
      "era": "근대",
      "category": "문화",
      "difficulty": 3,
      "id": 38041,
      "examId": 32,
      "questionNumber": 41,
      "keywords": [
        "한국독립운동지혈사",
        "진단 학회",
        "독사신론",
        "조선학 운동",
        "여유당전서"
      ],
      "explanation": "(가)는 일제강점기 민족의 독립 의지를 고취하고 민족정신을 강조한 박은식입니다. 박은식은 독립운동의 정당성을 알리고 민족정신을 고취하기 위해 「한국독립운동지혈사」를 저술하여 일제 침략에 맞선 독립 투쟁의 과정을 상세히 서술했습니다. 따라서 ①번 선지는 박은식의 활동으로 옳습니다.\n\n② 박은식은 민족의 혼을 강조하는 민족 사학을 주창했으며, 유물 사관은 식민 사학의 논리에 가깝습니다. ③ 진단 학회를 창립하여 실증주의 사학을 발전시킨 인물은 이병도, 신석호 등입니다. ④ 「독사신론」을 발표하여 민족을 역사 서술의 중심에 둔 인물은 신채호입니다. ⑤ 조선학 운동을 주도하며 「여유당전서」를 간행한 인물들은 정인보, 문일평, 안재홍 등입니다."
    },
    {
      "content": "(가) 인물의 활동으로 옳은 것은?",
      "choices": [
        "의열단을 조직하여 단장으로 활동하였다.",
        "동양척식 주식회사에 폭탄을 투척하였다.",
        "고종의 밀지를 받아 독립 의군부를 조직하였다.",
        "쌍성보 전투에서 한·중 연합 작전을 전개하였다.",
        "명동 성당 앞에서 이완용을 습격하여 중상을 입혔다."
      ],
      "correctAnswer": 4,
      "points": 2,
      "era": "근대",
      "category": "정치",
      "difficulty": 3,
      "id": 38042,
      "examId": 32,
      "questionNumber": 42,
      "keywords": [
        "의열단",
        "동양척식 주식회사",
        "독립 의군부",
        "쌍성보 전투",
        "이완용"
      ],
      "explanation": "(가) 인물은 1930년대 초 만주에서 한국독립군을 이끌며 중국군과 연합하여 항일전을 전개한 **지청천 장군**입니다. 특히 쌍성보 전투(1932년)는 지청천 장군의 한국독립군이 중국 호로군과 연합하여 일본군을 대파한 대표적인 승리이므로, ④번이 정답입니다.\n오답 해설: ① 의열단 조직은 김원봉, ② 동양척식 주식회사 폭탄 투척은 나석주, ③ 독립 의군부 조직은 임병찬, ⑤ 이완용 습격은 이재명 의사의 활동입니다."
    },
    {
      "content": "다음 두 의거를 일으킨 단체에 대한 설명으로 옳은 것은?",
      "choices": [
        "중·일 전쟁 발발 이후에 창설되었다.",
        "김구의 주도로 상하이에서 조직되었다.",
        "조선 혁명 선언을 활동 지침으로 하였다.",
        "김익상, 김상옥 등이 단원으로 활동하였다.",
        "일제가 꾸며낸 105인 사건으로 해체되었다."
      ],
      "correctAnswer": 2,
      "points": 2,
      "era": "근대",
      "category": "정치",
      "difficulty": 3,
      "id": 38043,
      "examId": 32,
      "questionNumber": 43,
      "keywords": [
        "김구",
        "상하이",
        "조선 혁명 선언",
        "김익상",
        "105인 사건"
      ],
      "explanation": "정답인 ②번 선지는 한인애국단에 대한 설명으로 옳습니다. 주어진 두 의거는 1932년 이봉창 의거와 윤봉길 의거를 의미하며, 이들을 주도한 단체는 대한민국 임시정부의 침체를 극복하고자 김구가 1931년 상하이에서 조직한 한인애국단입니다.\n\n*   **① 중·일 전쟁 발발 이후에 창설되었다.** 한인애국단은 1931년 만주사변 이후에 조직되었고, 중일 전쟁은 1937년에 발발했으므로 시기가 맞지 않습니다.\n*   **③ 조선 혁명 선언을 활동 지침으로 하였다.** 조선 혁명 선언(1923년 신채호 작성)은 의열단의 활동 지침이었습니다.\n*   **④ 김익상, 김상옥 등이 단원으로 활동하였다.** 김익상, 김상옥 등은 의열단 소속으로 활약했습니다.\n*   **⑤ 일제가 꾸며낸 105인 사건으로 해체되었다.** 105인 사건으로 해체된 단체는 신민회(1911년)입니다.\n\n한인애국단의 이봉창, 윤봉길 의거는 침체되어 있던 대한민국 임시정부에 새로운 활력을 불어넣고, 중국 국민당 정부와 국제 사회의 관심을 끌어 임시정부에 대한 지원을 확보하는 중요한 계기가 되었습니다. 특히 윤봉길 의거 이후 장제스(蔣介石)는 \"중국 100만 대군도 하지 못한 일을 한인 청년 한 명이 해냈다\"며 감탄하며 임시정부에 대한 전폭적인 지원을 약속했습니다."
    },
    {
      "content": "밑줄 그은 '시기'에 있었던 사실로 옳은 것은?",
      "choices": [
        "회사령이 철폐되었다.",
        "조선 태형령이 시행되었다.",
        "토지 조사 사업이 실시되었다.",
        "여자 정신 근로령이 공포되었다.",
        "제1차 조선 교육령이 발표되었다."
      ],
      "correctAnswer": 4,
      "points": 2,
      "era": "근대",
      "category": "사회",
      "difficulty": 3,
      "id": 38044,
      "examId": 32,
      "questionNumber": 44,
      "keywords": [
        "회사령",
        "조선 태형령",
        "토지 조사 사업",
        "제1차 조선 교육령"
      ]
    },
    {
      "content": "다음 가상 인터뷰의 주인공에 대한 설명으로 옳은 것은?",
      "choices": [
        "좌우 합작 위원회의 주축이 되었다.",
        "김규식과 함께 남북 협상에 참여하였다.",
        "재미 한인을 중심으로 흥사단을 설립하였다.",
        "정읍에서 남한만의 단독 정부 수립을 주장하였다.",
        "중국 국민당과 협력하여 조선의용대를 창설하였다."
      ],
      "correctAnswer": 1,
      "points": 3,
      "era": "현대",
      "category": "정치",
      "difficulty": 3,
      "id": 38045,
      "examId": 32,
      "questionNumber": 45,
      "keywords": [
        "흥사단",
        "김규식",
        "남북 협상",
        "단독 정부 수립",
        "조선의용대"
      ],
      "explanation": "이 문제의 주인공은 해방 직후 좌우익의 이념 대립을 해소하고 통일 임시정부 수립을 추진했던 인물로, 여운형 또는 김규식입니다.\n정답인 ① 좌우 합작 위원회는 1946년 좌우익 세력의 협력을 통해 통일 임시정부 수립을 목표로 결성되었으며, 여운형과 김규식이 그 주축이 되어 활동했습니다. 이는 분단 위기를 막으려 했던 주인공의 핵심적인 활동에 대한 올바른 설명입니다.\n오답인 ② 김규식과 함께 남북 협상에 참여한 인물은 김구이며, ③ 흥사단 설립은 안창호의 활동입니다. ④ 남한만의 단독 정부 수립을 주장한 것은 이승만이며, ⑤ 중국 국민당과 협력하여 조선의용대를 창설한 인물은 김원봉입니다."
    },
    {
      "content": "(가), (나) 사이의 시기에 있었던 사실로 옳은 것은?",
      "choices": [
        "정부 형태가 내각 책임제로 바뀌었다.",
        "장기 독재를 가능하게 한 유신 헌법이 공포되었다.",
        "평화 통일론을 주장한 진보당의 조봉암이 구속되었다.",
        "임시 수도 부산에서 대통령 직선제 개헌안이 통과되었다.",
        "여당 부통령 후보 당선을 위한 3.15 부정 선거가 자행되었다."
      ],
      "correctAnswer": 4,
      "points": 2,
      "era": "현대",
      "category": "정치",
      "difficulty": 3,
      "id": 38046,
      "examId": 32,
      "questionNumber": 46,
      "keywords": [
        "내각 책임제",
        "유신 헌법",
        "조봉암",
        "3.15 부정 선거",
        "대통령 직선제 개헌"
      ],
      "explanation": "정답 ④는 한국전쟁 중인 1952년, 이승만 정부가 피난 수도 부산에서 계엄령을 선포하고 국회를 압박하여 대통령 직선제를 내용으로 하는 개헌안을 통과시킨 이른바 '발췌 개헌'을 의미합니다. 이는 이승만이 간선제로는 재선이 어렵다고 판단하여 자신의 장기 집권을 위해 추진한 것으로, (가), (나) 사이의 시기에 일어난 이승만 정부의 권력 강화를 보여주는 중요한 사건입니다.\n\n오답 선지들은 모두 발췌 개헌 이후의 사건들입니다. ① 내각 책임제로의 정부 형태 변경은 4.19 혁명 이후 제2공화국에서(1960), ② 유신 헌법 공포는 박정희 정부에서(1972), ③ 평화 통일론을 주장한 진보당의 조봉암 구속은 이승만 정부 말기(1958), ⑤ 3.15 부정 선거 역시 이승만 정부 말기(1960)에 자행되었습니다."
    },
    {
      "content": "밑줄 그은 '총선거'에 대한 설명으로 옳지 않은 것은?",
      "choices": [
        "비례 대표제가 적용되었다.",
        "우리나라 최초의 보통 선거였다.",
        "38도선 이남 지역에서만 실시되었다.",
        "제헌 국회를 구성하기 위한 선거였다.",
        "제주도의 일부 지역에서 선거가 무효 처리되었다."
      ],
      "correctAnswer": 1,
      "points": 1,
      "era": "현대",
      "category": "정치",
      "difficulty": 3,
      "id": 38047,
      "examId": 32,
      "questionNumber": 47,
      "keywords": [
        "총선거",
        "보통 선거",
        "38도선",
        "제헌 국회",
        "제주도"
      ],
      "explanation": "정답은 ①번입니다. 1948년 5월 10일 실시된 제헌 국회의원 총선거는 소선거구제 방식으로 치러져 각 선거구에서 1명의 대표를 선출했으며, 비례 대표제는 이때 적용되지 않았습니다.\n\n이 선거는 대한민국 정부 수립의 기초를 마련하기 위한 우리나라 최초의 보통 선거였으며, UN 소총회 결정에 따라 38도선 이남 지역에서만 실시되었습니다. 선거를 통해 제헌 국회를 구성했고, 제주 4.3 사건의 여파로 제주도의 일부 지역에서는 선거가 무효 처리되기도 했습니다."
    },
    {
      "content": "다음 뉴스에 보도된 사건 이후의 사실로 옳은 것을 <보기>에서 고른 것은?",
      "choices": [
        "ㄱ,ㄴ",
        "ㄱ,ㄷ",
        "ㄴ,ㄷ",
        "ㄴ,ㄹ",
        "ㄷ,ㄹ"
      ],
      "correctAnswer": 2,
      "points": 3,
      "era": "현대",
      "category": "사회",
      "difficulty": 3,
      "id": 38048,
      "examId": 32,
      "questionNumber": 48,
      "keywords": [
        "사건",
        "뉴스",
        "현대"
      ],
      "explanation": "뉴스에 보도된 사건이 1987년 6월 민주 항쟁을 의미한다면, ㄱ. 대통령 직선제 개헌과 ㄷ. 지방 자치제 전면 실시는 그 이후에 전개된 사실입니다. 6월 민주 항쟁 이후 6.29 선언을 통해 대통령 직선제 개헌(1987년 10월)이 이루어졌고, 이어진 문민 정부 시기인 1995년에는 지방 자치제가 전면 실시되며 민주화가 심화되었습니다. 6월 민주 항쟁은 국민들의 직접 선거 요구가 관철된 한국 현대사의 중요한 민주화 전환점으로, 이 사건 이전의 유신 체제 수립(1972)이나 5.18 민주화 운동(1980) 등은 오답에 해당합니다."
    },
    {
      "content": "(가), (나) 인물이 대통령으로 재임했던 시기에 있었던 사실로 옳은 것을 <보기>에서 고른 것은?",
      "choices": [
        "ㄱ,ㄴ",
        "ㄱ,ㄷ",
        "ㄴ,ㄷ",
        "ㄴ,ㄹ",
        "ㄷ,ㄹ"
      ],
      "correctAnswer": 3,
      "points": 2,
      "era": "현대",
      "category": "정치",
      "difficulty": 3,
      "id": 38049,
      "examId": 32,
      "questionNumber": 49,
      "keywords": [
        "인물",
        "대통령",
        "재임",
        "현대"
      ],
      "explanation": "문제의 (가), (나) 인물이 대통령으로 재임했던 시기는 **전두환 대통령**의 제5공화국 시기(1980~1988)를 의미합니다. 이 시기 ㄴ. **3저 호황**은 국제 유가, 금리, 달러 가치 하락이라는 유리한 국제 환경 속에서 한국 경제가 크게 성장한 현상이며, ㄷ. **6월 민주 항쟁**은 1987년 대통령 직선제 개헌을 요구하며 전국적으로 일어난 민주화 운동입니다. 두 사건 모두 전두환 정부 시기에 발생했던 주요 사실이므로 정답은 ③입니다. (다른 선지들은 박정희 정부의 유신 헌법 제정, 김영삼 정부의 금융실명제 실시 등 다른 시기에 해당합니다.)"
    },
    {
      "content": "다음 선언문을 발표한 민주화 운동에 대한 설명으로 옳은 것은?",
      "choices": [
        "양원제 국회가 출현하는 결과를 가져왔다.",
        "굴욕적인 한·일 국교 정상화에 반대하였다.",
        "신군부의 비상 계엄 확대가 원인이 되어 일어났다.",
        "관련 자료가 유네스코 세계 기록 유산으로 등재되었다.",
        "5년 단임의 대통령 직선제 개헌이 이루어지는 계기가 되었다."
      ],
      "correctAnswer": 5,
      "points": 2,
      "era": "현대",
      "category": "정치",
      "difficulty": 3,
      "id": 38050,
      "examId": 32,
      "questionNumber": 50,
      "keywords": [
        "신군부",
        "비상 계엄",
        "유네스코 세계 기록 유산",
        "대통령 직선제 개헌"
      ],
      "explanation": "제시된 선언문은 6월 민주 항쟁(1987년)과 관련된 것으로, ⑤번은 이 운동의 핵심적인 성과를 정확히 설명합니다. 6월 민주 항쟁은 전두환 정권의 4·13 호헌조치에 반발하여 대통령 직선제 개헌을 강력히 요구했고, 그 결과 국민적 요구가 수용되어 현행 헌법인 5년 단임 대통령 직선제가 확립되었습니다.\n\n① 양원제 국회는 제2공화국(장면 내각) 시기에 운영되었습니다. ② 굴욕적인 한·일 국교 정상화 반대는 1964년 6·3 시위(박정희 정부)와 관련이 있습니다. ③ 신군부의 비상 계엄 확대는 1980년 5·18 광주 민주화 운동의 주요 원인이었습니다. ④ 관련 자료의 유네스코 세계 기록 유산 등재는 주로 5·18 광주 민주화 운동 기록물과 관련됩니다."
    }
  ]
}