{
  "id": "s1-07",
  "title": "통일신라 왕업적표",
  "era": "삼국",
  "eraLabel": "고대/중세 (삼국·남북국)",
  "sectionId": "s1",
  "content": "<details><summary><strong>👑 통일신라 왕업적표</strong></summary><div class=\"content\">\n    <div class=\"note\">⚡ 통일신라는 <span class=\"highlight\">중대(무열왕계, 전제왕권 강화)</span>와 <span class=\"highlight\">하대(진골 귀족 간 왕위 쟁탈)</span>로 구분됩니다. 중대 왕들의 체제 정비 업적이 시험에 자주 출제되며, 특히 <span class=\"keyword\">신문왕</span>의 개혁 정책은 거의 매회 출제됩니다.</div>\n\n    <details class=\"sub-details\"><summary>통일신라 시대 구분</summary><div class=\"content\">\n        <table>\n            <thead>\n                <tr><th>구분</th><th>중대 (654~780)</th><th>하대 (780~935)</th></tr>\n            </thead>\n            <tbody>\n                <tr>\n                    <td>왕계</td>\n                    <td><span class=\"keyword\">무열왕계</span> (김춘추 직계)</td>\n                    <td><span class=\"keyword\">내물왕계</span> (원성왕 이후)</td>\n                </tr>\n                <tr>\n                    <td>왕권</td>\n                    <td><span class=\"highlight\">전제왕권 강화</span>, 왕이 국정 주도</td>\n                    <td><span class=\"highlight\">왕권 약화</span>, 진골 귀족 간 왕위 쟁탈</td>\n                </tr>\n                <tr>\n                    <td>전환점</td>\n                    <td colspan=\"2\"><span class=\"keyword\">혜공왕</span> 피살(780)로 중대 종결 → 하대 시작</td>\n                </tr>\n                <tr>\n                    <td>사회 변화</td>\n                    <td>중앙집권 체제 안정, 제도 정비 완료</td>\n                    <td>호족 성장, 6두품 불만, 선종·풍수지리 유행</td>\n                </tr>\n            </tbody>\n        </table>\n    </div></details>\n\n    <details class=\"sub-details\"><summary>통일신라 중대 왕별 업적표 (무열왕~혜공왕)</summary><div class=\"content\">\n        <table>\n            <thead>\n                <tr><th>왕</th><th>재위</th><th>주요 업적</th></tr>\n            </thead>\n            <tbody>\n                <tr>\n                    <td><span class=\"keyword\">무열왕</span><br>(태종)</td>\n                    <td>654~661</td>\n                    <td>\n                        <ul>\n                            <li>최초의 <span class=\"highlight\">진골 출신 왕</span> (진덕여왕 이후 성골 단절)</li>\n                            <li><span class=\"highlight\">나당동맹</span> 체결(648, 김춘추가 당 태종과 직접 교섭)</li>\n                            <li>나당연합군으로 <span class=\"highlight\">백제 멸망</span>(660, 사비성 함락)</li>\n                            <li>무열왕계 왕통의 시작 → 중대의 첫 왕</li>\n                        </ul>\n                    </td>\n                </tr>\n                <tr>\n                    <td><span class=\"keyword\">문무왕</span></td>\n                    <td>661~681</td>\n                    <td>\n                        <ul>\n                            <li>나당연합군으로 <span class=\"highlight\">고구려 멸망</span>(668, 평양성 함락)</li>\n                            <li><span class=\"highlight\">나당전쟁</span> 승리 — <span class=\"keyword\">매소성 전투</span>(675), <span class=\"keyword\">기벌포 전투</span>(676)</li>\n                            <li><span class=\"highlight\">삼국통일 완성</span>(676, 대동강~원산만 이남 확보)</li>\n                            <li>안승에게 보덕국(금마저, 전북 익산) 설치 허용</li>\n                            <li>유언으로 동해 <span class=\"keyword\">대왕암</span>에 장례 — 호국룡(護國龍) 설화</li>\n                        </ul>\n                    </td>\n                </tr>\n                <tr>\n                    <td><span class=\"keyword\">신문왕</span></td>\n                    <td>681~692</td>\n                    <td>\n                        <ul>\n                            <li>⭐ <span class=\"highlight\">통일신라 체제 정비의 완성자</span></li>\n                            <li><span class=\"keyword\">김흠돌의 난</span> 진압 → 반대파 귀족 대규모 숙청으로 왕권 강화</li>\n                            <li><span class=\"highlight\">국학</span> 설립 (유교 교육기관, 오경 교육)</li>\n                            <li><span class=\"highlight\">9주 5소경</span> 정비 — 전국을 9개 주, 5개 소경으로 나눈 지방 행정 체계 완성</li>\n                            <li><span class=\"highlight\">9서당 10정</span> 완비 — 9서당(중앙군), 10정(지방군)의 군사 체계 확립</li>\n                            <li><span class=\"highlight\">관료전</span> 지급 + <span class=\"highlight\">녹읍 폐지</span> → 귀족의 경제적 기반 약화, 왕권 강화</li>\n                            <li><span class=\"keyword\">만파식적</span> 설화 — 피리를 불면 적이 물러간다는 이야기로 왕권의 정당성 표현</li>\n                        </ul>\n                    </td>\n                </tr>\n                <tr>\n                    <td><span class=\"keyword\">성덕왕</span></td>\n                    <td>702~737</td>\n                    <td>\n                        <ul>\n                            <li><span class=\"highlight\">정전 지급</span>(722) — 백성(정남)에게 토지를 지급하여 농민 생활 안정</li>\n                            <li>재위 35년, 통일 이후 신라 왕 중 <span class=\"highlight\">최장 재위</span> 기록</li>\n                            <li><span class=\"keyword\">성덕대왕신종</span>(에밀레종) 주조 시작 (경덕왕 때 완성)</li>\n                            <li>당과의 외교 안정, 신라 국력의 전성기</li>\n                        </ul>\n                    </td>\n                </tr>\n                <tr>\n                    <td><span class=\"keyword\">경덕왕</span></td>\n                    <td>742~765</td>\n                    <td>\n                        <ul>\n                            <li><span class=\"highlight\">한화 정책</span> — 관청명·지명을 중국식(한자)으로 변경 (현재 지명의 기원)</li>\n                            <li><span class=\"keyword\">국학</span>을 <span class=\"keyword\">태학감</span>으로 개칭</li>\n                            <li><span class=\"keyword\">녹읍 부활</span> — 귀족 세력과 타협하여 녹읍을 다시 허용</li>\n                            <li><span class=\"keyword\">불국사</span>·<span class=\"keyword\">석굴암</span> 창건 (재상 김대성이 주도)</li>\n                            <li><span class=\"keyword\">성덕대왕신종</span>(에밀레종) 완성</li>\n                        </ul>\n                    </td>\n                </tr>\n                <tr>\n                    <td><span class=\"keyword\">혜공왕</span></td>\n                    <td>765~780</td>\n                    <td>\n                        <ul>\n                            <li><span class=\"highlight\">무열왕계의 마지막 왕</span> — 중대의 종결</li>\n                            <li>8세의 어린 나이로 즉위하여 태후가 섭정</li>\n                            <li>96각간의 난, 김지정의 난 등 <span class=\"highlight\">귀족 반란이 끊이지 않음</span></li>\n                            <li>피살당하며 중대 종결 → <span class=\"highlight\">하대 개막</span> (본격적 왕위 쟁탈전 시작)</li>\n                        </ul>\n                    </td>\n                </tr>\n            </tbody>\n        </table>\n    </div></details>\n\n    <details class=\"sub-details\"><summary>통일신라 하대 주요 왕</summary><div class=\"content\">\n        <table>\n            <thead>\n                <tr><th>왕</th><th>재위</th><th>주요 사항</th></tr>\n            </thead>\n            <tbody>\n                <tr>\n                    <td><span class=\"keyword\">원성왕</span></td>\n                    <td>785~798</td>\n                    <td><span class=\"highlight\">독서삼품과</span> 실시 — 유학 실력(유교 경전 이해도)에 따라 관리 선발. 골품제의 한계를 극복하려는 시도였으나 진골 귀족의 반발로 실효 미미</td>\n                </tr>\n                <tr>\n                    <td><span class=\"keyword\">헌덕왕</span></td>\n                    <td>809~826</td>\n                    <td><span class=\"keyword\">김헌창의 난</span>(822) — 웅주(공주) 도독이 반란, '장안국' 건국 선포. 아들 김범문도 이듬해 반란 → 지방 세력의 중앙 이탈 현상 본격화</td>\n                </tr>\n                <tr>\n                    <td><span class=\"keyword\">흥덕왕</span></td>\n                    <td>826~836</td>\n                    <td><span class=\"keyword\">장보고</span>가 <span class=\"highlight\">청해진</span>(완도) 설치(828) — 해적 소탕, 해상 무역권 장악. 당·일본과의 국제 무역 주도</td>\n                </tr>\n                <tr>\n                    <td><span class=\"keyword\">진성여왕</span></td>\n                    <td>887~897</td>\n                    <td>정치 문란, 조세 수취 강화 → 전국적 농민 봉기 발생. <span class=\"keyword\">원종·애노의 난</span>(889, 사벌주) → <span class=\"highlight\">후삼국 시대</span> 개막의 신호탄</td>\n                </tr>\n            </tbody>\n        </table>\n    </div></details>\n\n    <details class=\"sub-details\"><summary>신문왕의 체제 정비 한눈에 보기</summary><div class=\"content\">\n        <p><span class=\"keyword\">신문왕</span>은 11년이라는 짧은 재위 기간에도 불구하고 통일신라의 중앙집권 체제를 완성한 군주입니다. 할아버지(무열왕)와 아버지(문무왕)가 삼국통일이라는 외적 과업을 달성했다면, 신문왕은 내부 체제 정비라는 수성(守成)의 과업을 완수했습니다.</p>\n        <table>\n            <thead>\n                <tr><th>분야</th><th>정책</th><th>의미</th></tr>\n            </thead>\n            <tbody>\n                <tr><td>정치</td><td><span class=\"keyword\">김흠돌의 난</span> 진압, 귀족 숙청</td><td>반대 세력 제거로 전제왕권 확립</td></tr>\n                <tr><td>교육</td><td><span class=\"keyword\">국학</span> 설립 (유교 경전 교육)</td><td>유교 이념에 기반한 관리 양성 체계 구축</td></tr>\n                <tr><td>행정</td><td><span class=\"keyword\">9주 5소경</span> 정비</td><td>전국 지방 행정 체계 완성</td></tr>\n                <tr><td>군사</td><td><span class=\"keyword\">9서당 10정</span> 완비</td><td>중앙군(9서당) + 지방군(10정) 체계 확립</td></tr>\n                <tr><td>경제</td><td><span class=\"keyword\">녹읍 폐지</span>, <span class=\"keyword\">관료전</span> 지급</td><td>귀족의 경제적 기반 약화, 왕에 대한 경제적 종속 강화</td></tr>\n                <tr><td>감찰</td><td><span class=\"keyword\">외사정</span> 파견</td><td>지방관의 비위를 감찰하여 중앙 통제력 강화</td></tr>\n            </tbody>\n        </table>\n    </div></details>\n\n    <details class=\"sub-details\"><summary>📌 시험 핵심 키워드</summary><div class=\"content\">\n        <table>\n            <thead>\n                <tr><th>구분</th><th>핵심 키워드</th></tr>\n            </thead>\n            <tbody>\n                <tr>\n                    <td>중대 시작</td>\n                    <td><span class=\"keyword\">무열왕</span> = 최초 진골 왕, 나당동맹, 백제 멸망(660)</td>\n                </tr>\n                <tr>\n                    <td>삼국통일</td>\n                    <td><span class=\"keyword\">문무왕</span> = 고구려 멸망(668) + 나당전쟁 승리(매소성·기벌포, 676)</td>\n                </tr>\n                <tr>\n                    <td>체제 정비</td>\n                    <td><span class=\"keyword\">신문왕</span> = 국학 + 9주5소경 + 9서당10정 + 녹읍 폐지 + 관료전</td>\n                </tr>\n                <tr>\n                    <td>토지 제도 변천</td>\n                    <td><span class=\"keyword\">신문왕</span>(녹읍 폐지·관료전) → <span class=\"keyword\">성덕왕</span>(정전) → <span class=\"keyword\">경덕왕</span>(녹읍 부활)</td>\n                </tr>\n                <tr>\n                    <td>하대 전환</td>\n                    <td><span class=\"keyword\">혜공왕</span> 피살(780) → 무열왕계 단절 → 하대(왕위 쟁탈전)</td>\n                </tr>\n                <tr>\n                    <td>하대 핵심</td>\n                    <td><span class=\"keyword\">원성왕</span>(독서삼품과), <span class=\"keyword\">흥덕왕</span>(장보고·청해진), <span class=\"keyword\">진성여왕</span>(후삼국 개막)</td>\n                </tr>\n            </tbody>\n        </table>\n    </div></details>\n</div></details>",
  "relatedKeywords": [
    "청해진",
    "독서삼품과",
    "관료전",
    "녹읍",
    "상수리 제도",
    "김춘추",
    "신라",
    "9서당 10정",
    "삼국",
    "김흠돌",
    "고구려",
    "국학",
    "태학",
    "성왕",
    "외사정",
    "김흠돌의 난",
    "김헌창",
    "화왕계",
    "9서당",
    "장보고",
    "당항성",
    "제도",
    "상대등",
    "이두",
    "울산항",
    "불국사",
    "석가탑",
    "5소경",
    "아라비아 상인",
    "상인",
    "왕권 강화",
    "무열왕",
    "전쟁",
    "신문",
    "원성왕",
    "녹읍 폐지",
    "10정",
    "무왕",
    "문무왕",
    "서시",
    "남시",
    "서당",
    "왕위 계승",
    "활동",
    "삼국통일",
    "진골",
    "혜공왕",
    "울산",
    "진골 귀족"
  ],
  "relatedQuestionIds": [
    6004,
    6005,
    6006,
    8007,
    8008,
    8010,
    10006,
    10009,
    10015,
    11007,
    11029,
    11030,
    12007,
    12019,
    12047,
    14004,
    16002,
    16005,
    16007,
    16038,
    17005,
    17011,
    18003,
    18007,
    18009,
    18024,
    19005,
    19008,
    19025,
    20006,
    22006,
    22027,
    23008,
    23012,
    25005,
    25008,
    25009,
    25011,
    25049,
    26004,
    26005,
    26008,
    26011,
    26013,
    27007,
    27009,
    27018,
    28004,
    28017,
    28029,
    29003,
    29005,
    29007,
    29010,
    29018,
    29026,
    30007,
    30009,
    30013,
    31007,
    31008,
    31009,
    31010,
    31011,
    31012,
    32005,
    32008,
    32017,
    33003,
    33011,
    33013,
    33022,
    33038,
    34002,
    34004,
    34006,
    34007,
    34009,
    34010,
    34011,
    34012,
    34013,
    35003,
    35006,
    35010,
    35013,
    35015,
    36007,
    36011,
    37004,
    37005,
    37007,
    37011,
    37034,
    38003,
    38010,
    39006,
    39008,
    39009,
    39010,
    39011,
    40005,
    40006,
    40007,
    40008,
    40010,
    41007,
    41010,
    42009,
    42012,
    43004,
    43008,
    43009,
    43012,
    43014,
    43017,
    44003,
    44008,
    44010,
    45007,
    45010,
    45017,
    45020,
    46007,
    46008,
    46009,
    47006,
    47010,
    47011,
    48006,
    48008,
    48012,
    48016,
    49001,
    49002,
    49006,
    51007,
    51008,
    51010,
    51011,
    51016,
    52006,
    52009,
    52032,
    53006,
    53007,
    54004,
    54006,
    54007,
    55003,
    55009,
    55012,
    56003,
    56005,
    56009,
    56010,
    56035,
    57006,
    57008,
    57009,
    57010,
    58003,
    58009,
    58010,
    58014,
    59007,
    59008,
    59009,
    59018,
    59022,
    60006,
    60008,
    61004,
    61006,
    61007,
    61008,
    61010,
    61011,
    61025,
    61029,
    62003,
    62005,
    62007,
    62008,
    62009,
    63003,
    63005,
    63006,
    63007,
    63012,
    63013,
    64013,
    64050,
    65003,
    65006,
    65007,
    65008,
    65009,
    65035,
    66007,
    66008,
    66009,
    67005,
    67007,
    67008,
    67009,
    68004,
    68005,
    68008,
    69002,
    69008,
    69012,
    69048,
    70007,
    70008,
    71006,
    71008,
    71013,
    71014,
    72003,
    72005,
    72006,
    72007,
    72008,
    73002,
    73007,
    73009,
    74004,
    74006,
    74007,
    74009,
    74050,
    75006,
    75008,
    75009,
    75016,
    76005,
    76006,
    76009,
    76013,
    77006,
    77007,
    77008,
    77014,
    77015,
    77025
  ],
  "order": 6
}