{
  "id": "s7-08",
  "title": "️ 제2공화국 (1960.6~1961.5)",
  "era": "현대",
  "eraLabel": "현대",
  "sectionId": "s7",
  "content": "  <details open>\r\n    <summary>🏛️ 제2공화국 (1960.6~1961.5)</summary>\r\n    <div class=\"content\">\r\n      <p><strong>정부 구성</strong></p>\r\n      <ul>\r\n        <li><strong>대통령</strong>: 윤보선</li>\r\n        <li><strong>국무총리</strong>: 장면</li>\r\n      </ul>\r\n\r\n      <p><strong>정치 체제</strong></p>\r\n      <ul>\r\n        <li><span class=\"highlight\">유일했던 양원제 의원 내각제</span></li>\r\n        <li>내각책임제</li>\r\n        <li>민의원 + 참의원</li>\r\n      </ul>\r\n\r\n      <p><strong>주요 정책</strong></p>\r\n      <ul>\r\n        <li>민주 개혁 시도</li>\r\n        <li>경제 개발 5개년 계획 수립</li>\r\n        <li>평화통일 추진</li>\r\n        <li>3차, 4차 개헌</li>\r\n      </ul>\r\n\r\n      <p><strong>주요 활동</strong></p>\r\n      <ul>\r\n        <li>민족통일전국학생연맹: 남북학생회담 추진 ('가자 북으로, 오라 남으로')</li>\r\n        <li><span class=\"badge\">1953.06</span> <strong>반공포로 석방사건</strong>: 한국측이 유엔군의 동의 없이 거제도 포로수용소의 반공포로 석방</li>\r\n      </ul>\r\n    </div>\r\n  </details>\r",
  "relatedKeywords": [
    "경제 개발 5개년 계획",
    "사건",
    "국학",
    "양원제",
    "의원 내각제",
    "제도",
    "민의원",
    "참의원",
    "대통령",
    "정부",
    "정책",
    "활동",
    "구성",
    "유엔",
    "개헌",
    "거제도 포로수용소"
  ],
  "relatedQuestionIds": [
    8049,
    10049,
    12047,
    14004,
    14029,
    16047,
    16050,
    17011,
    22006,
    22050,
    23049,
    25005,
    25008,
    25009,
    25045,
    25048,
    25049,
    25050,
    27045,
    27047,
    27049,
    27050,
    28017,
    28028,
    29007,
    29018,
    29026,
    29031,
    30047,
    31011,
    31041,
    31047,
    33003,
    34009,
    34010,
    34047,
    37005,
    37047,
    38002,
    38048,
    38049,
    39049,
    42045,
    43049,
    44003,
    44048,
    46045,
    48048,
    52021,
    54047,
    56049,
    60042,
    60044,
    62044,
    63041,
    63042,
    69043,
    69046,
    72040,
    72046,
    74048
  ],
  "order": 78
}